{
  "$id": "https://meta.secondarymetabolites.org/schemas/mibig/common/substrate_evidence.json",
  "$schema": "https://json-schema.org/draft/2020-12/schema",
  "type": "object",
  "additionalProperties": false,
  "properties": {
    "method": {
      "type": "string",
      "enum": [
        "Activity assay",
        "ACVS assay",
        "ATP-PPi exchange assay",
        "Enzyme-coupled assay",
        "Feeding study",
        "Heterologous expression",
        "Homology",
        "HPLC",
        "In-vitro experiments",
        "Knock-out studies",
        "Mass spectrometry",
        "NMR",
        "Radio labelling",
        "Sequence-based prediction",
        "Steady-state kinetics",
        "Structure-based inference",
        "X-ray crystallography"
      ]
    },
    "references": {
      "type": "array",
      "items": {
        "$ref": "/schemas/common/citation.json"
      },
      "minItems": 1,
      "uniqueItems": true
    }
  },
  "required": ["method", "references"]
}
